litext.py
litext-0.1.dist-info/METADATA
litext-0.1.dist-info/WHEEL
litext-0.1.dist-info/top_level.txt
litext-0.1.dist-info/RECORD
