Metadata-Version: 2.1
Name: litext
Version: 0.1
Summary: Simple search engine built on top of SQLite
Home-page: https://github.com/litements/litext
Author: Ricardo Ander-Egg Aguilar
Author-email: rsubacc@gmail.com
License: UNKNOWN
Platform: UNKNOWN
Classifier: Operating System :: OS Independent
Requires-Python: >=3.7
Requires-Dist: sqlite-spellfix
Requires-Dist: sqlite-utils
